crypto/__init__.py
crypto/app.py
crypto/decryptoapp.py
crypto/settings.py
crypto/commands/__init__.py
crypto/library/__init__.py
crypto/library/cryptor.py
crypto/library/hash.py
crypto/library/package.py
crypto-1.4.0.data/scripts/crypto
crypto-1.4.0.data/scripts/decrypto
crypto-1.4.0.dist-info/DESCRIPTION.rst
crypto-1.4.0.dist-info/entry_points.txt
crypto-1.4.0.dist-info/METADATA
crypto-1.4.0.dist-info/pydist.json
crypto-1.4.0.dist-info/RECORD
crypto-1.4.0.dist-info/top_level.txt
crypto-1.4.0.dist-info/WHEEL
