Metadata-Version: 1.1
Name: crypto
Version: 1.4.0
Summary: Simple symmetric GPG file encryption and decryption
Home-page: https://github.com/chrissimpkins/crypto
Author: Christopher Simpkins
Author-email: git.simpkins@gmail.com
License: MIT license
Keywords: encryption,decryption,gpg,pgp,openpgp,cipher,AES256,crypto,cryptography,security,privacy
Platform: any
Classifier: Intended Audience :: End Users/Desktop
Classifier: Topic :: Security :: Cryptography
Classifier: Topic :: Security
Classifier: Development Status :: 5 - Production/Stable
Classifier: Natural Language :: English
Classifier: License :: OSI Approved :: MIT License
Classifier: Operating System :: MacOS :: MacOS X
Classifier: Operating System :: POSIX
Classifier: Operating System :: Unix
Classifier: Programming Language :: Python
Classifier: Programming Language :: Python :: 2
Classifier: Programming Language :: Python :: 3
